AUTHORS.rst
CHANGES.rst
MANIFEST.in
README.rst
TODO.rst
setup.cfg
setup.py
birdhousebuilder/__init__.py
birdhousebuilder.recipe.postgres.egg-info/PKG-INFO
birdhousebuilder.recipe.postgres.egg-info/SOURCES.txt
birdhousebuilder.recipe.postgres.egg-info/dependency_links.txt
birdhousebuilder.recipe.postgres.egg-info/entry_points.txt
birdhousebuilder.recipe.postgres.egg-info/namespace_packages.txt
birdhousebuilder.recipe.postgres.egg-info/not-zip-safe
birdhousebuilder.recipe.postgres.egg-info/pbr.json
birdhousebuilder.recipe.postgres.egg-info/requires.txt
birdhousebuilder.recipe.postgres.egg-info/top_level.txt
birdhousebuilder/recipe/__init__.py
birdhousebuilder/recipe/postgres/__init__.py
birdhousebuilder/recipe/postgres/postgresql.conf
birdhousebuilder/recipe/postgres/tests/__init__.py
birdhousebuilder/recipe/postgres/tests/test_postgresdocs.py