Metadata-Version: 1.1
Name: birdhousebuilder.recipe.postgres
Version: 0.2.0
Summary: A Buildout recipe to install and configure Postgres database with Anaconda.
Home-page: https://github.com/bird-house/birdhousebuilder.recipe.postgres
Author: Birdhouse
Author-email: UNKNOWN
License: GPL v2
Keywords: buildout recipe postgres birdhouse anaconda
Platform: UNKNOWN
Classifier: Framework :: Buildout
Classifier: Intended Audience :: Developers
Classifier: Topic :: Software Development :: Build Tools
Classifier: Topic :: Software Development :: Libraries :: Python Modules
Classifier: License :: OSI Approved :: GNU General Public License v2 (GPLv2)
